[
    {
        "temperature": 8.4,
        "relative_humidity": 82,
        "dew_point": 5.5,
        "apparent_temperature": 7.0,
        "precipitation_probability": 35,
        "rain": 0.0,
        "surface_pressure": 975.4
    },
    {
        "temperature": 9.3,
        "relative_humidity": 72,
        "dew_point": 4.5,
        "apparent_temperature": 7.6,
        "precipitation_probability": 35,
        "rain": 0.0,
        "surface_pressure": 977.1
    },
    {
        "temperature": 9.2,
        "relative_humidity": 72,
        "dew_point": 4.4,
        "apparent_temperature": 7.5,
        "precipitation_probability": 35,
        "rain": 0.0,
        "surface_pressure": 976.5
    },
    {
        "temperature": 8.2,
        "relative_humidity": 92,
        "dew_point": 6.9,
        "apparent_temperature": 6.9,
        "precipitation_probability": 35,
        "rain": 0.0,
        "surface_pressure": 977.2
    },
    {
        "temperature": 8.2,
        "relative_humidity": 92,
        "dew_point": 7.0,
        "apparent_temperature": 7.0,
        "precipitation_probability": 35,
        "rain": 0.0,
        "surface_pressure": 978.5
    },
    {
        "temperature": 9.2,
        "relative_humidity": 72,
        "dew_point": 4.5,
        "apparent_temperature": 7.5,
        "precipitation_probability": 35,
        "rain": 0.0,
        "surface_pressure": 976.8
    },
    {
        "temperature": 9.0,
        "relative_humidity": 70,
        "dew_point": 3.8,
        "apparent_temperature": 6.6,
        "precipitation_probability": 35,
        "rain": 0.0,
        "surface_pressure": 976.0
    },
    {
        "temperature": 9.2,
        "relative_humidity": 72,
        "dew_point": 4.5,
        "apparent_temperature": 7.5,
        "precipitation_probability": 35,
        "rain": 0.0,
        "surface_pressure": 976.8
    },
    {
        "temperature": 9.2,
        "relative_humidity": 72,
        "dew_point": 4.4,
        "apparent_temperature": 7.5,
        "precipitation_probability": 35,
        "rain": 0.0,
        "surface_pressure": 976.1
    },
    {
        "temperature": 9.2,
        "relative_humidity": 72,
        "dew_point": 4.4,
        "apparent_temperature": 7.5,
        "precipitation_probability": 35,
        "rain": 0.0,
        "surface_pressure": 976.0
    },
    {
        "temperature": 9.2,
        "relative_humidity": 72,
        "dew_point": 4.5,
        "apparent_temperature": 7.5,
        "precipitation_probability": 35,
        "rain": 0.0,
        "surface_pressure": 976.8
    },
    {
        "temperature": 8.4,
        "relative_humidity": 82,
        "dew_point": 5.5,
        "apparent_temperature": 7.1,
        "precipitation_probability": 35,
        "rain": 0.0,
        "surface_pressure": 975.9
    },
    {
        "temperature": 9.2,
        "relative_humidity": 72,
        "dew_point": 4.4,
        "apparent_temperature": 7.5,
        "precipitation_probability": 35,
        "rain": 0.0,
        "surface_pressure": 976.0
    },
    {
        "temperature": 8.1,
        "relative_humidity": 92,
        "dew_point": 6.9,
        "apparent_temperature": 6.9,
        "precipitation_probability": 35,
        "rain": 0.0,
        "surface_pressure": 976.3
    },
    {
        "temperature": 8.4,
        "relative_humidity": 82,
        "dew_point": 5.5,
        "apparent_temperature": 7.1,
        "precipitation_probability": 35,
        "rain": 0.0,
        "surface_pressure": 976.0
    },
    {
        "temperature": 9.0,
        "relative_humidity": 70,
        "dew_point": 3.8,
        "apparent_temperature": 6.6,
        "precipitation_probability": 32,
        "rain": 0.0,
        "surface_pressure": 975.6
    },
    {
        "temperature": 9.3,
        "relative_humidity": 72,
        "dew_point": 4.5,
        "apparent_temperature": 7.6,
        "precipitation_probability": 35,
        "rain": 0.0,
        "surface_pressure": 978.0
    },
    {
        "temperature": 8.1,
        "relative_humidity": 92,
        "dew_point": 6.9,
        "apparent_temperature": 6.9,
        "precipitation_probability": 35,
        "rain": 0.0,
        "surface_pressure": 976.0
    },
    {
        "temperature": 8.1,
        "relative_humidity": 92,
        "dew_point": 6.9,
        "apparent_temperature": 6.9,
        "precipitation_probability": 35,
        "rain": 0.0,
        "surface_pressure": 976.4
    },
    {
        "temperature": 9.2,
        "relative_humidity": 72,
        "dew_point": 4.4,
        "apparent_temperature": 7.5,
        "precipitation_probability": 35,
        "rain": 0.0,
        "surface_pressure": 976.2
    },
    {
        "temperature": 9.2,
        "relative_humidity": 72,
        "dew_point": 4.4,
        "apparent_temperature": 7.5,
        "precipitation_probability": 35,
        "rain": 0.0,
        "surface_pressure": 975.9
    },
    {
        "temperature": 8.1,
        "relative_humidity": 92,
        "dew_point": 6.9,
        "apparent_temperature": 6.9,
        "precipitation_probability": 35,
        "rain": 0.0,
        "surface_pressure": 977.0
    },
    {
        "temperature": 9.3,
        "relative_humidity": 72,
        "dew_point": 4.5,
        "apparent_temperature": 7.6,
        "precipitation_probability": 35,
        "rain": 0.0,
        "surface_pressure": 978.2
    },
    {
        "temperature": 8.4,
        "relative_humidity": 82,
        "dew_point": 5.5,
        "apparent_temperature": 7.1,
        "precipitation_probability": 35,
        "rain": 0.0,
        "surface_pressure": 976.0
    },
    {
        "temperature": 9.4,
        "relative_humidity": 66,
        "dew_point": 3.3,
        "apparent_temperature": 6.4,
        "precipitation_probability": 35,
        "rain": 0.0,
        "surface_pressure": 975.6
    },
    {
        "temperature": 8.4,
        "relative_humidity": 82,
        "dew_point": 5.5,
        "apparent_temperature": 7.1,
        "precipitation_probability": 35,
        "rain": 0.0,
        "surface_pressure": 976.2
    },
    {
        "temperature": 8.3,
        "relative_humidity": 92,
        "dew_point": 7.1,
        "apparent_temperature": 7.1,
        "precipitation_probability": 35,
        "rain": 0.0,
        "surface_pressure": 979.4
    },
    {
        "temperature": 9.0,
        "relative_humidity": 70,
        "dew_point": 3.8,
        "apparent_temperature": 6.7,
        "precipitation_probability": 32,
        "rain": 0.0,
        "surface_pressure": 976.1
    },
    {
        "temperature": 8.1,
        "relative_humidity": 92,
        "dew_point": 6.9,
        "apparent_temperature": 6.9,
        "precipitation_probability": 35,
        "rain": 0.0,
        "surface_pressure": 976.4
    }
]