[
    {
        "temperature": 16.8,
        "relative_humidity": 53,
        "dew_point": 7.2,
        "apparent_temperature": 12.7,
        "precipitation_probability": 0,
        "rain": 0.0,
        "surface_pressure": 961.9
    },
    {
        "temperature": 17.4,
        "relative_humidity": 51,
        "dew_point": 7.2,
        "apparent_temperature": 14.1,
        "precipitation_probability": 0,
        "rain": 0.0,
        "surface_pressure": 963.4
    },
    {
        "temperature": 17.4,
        "relative_humidity": 51,
        "dew_point": 7.1,
        "apparent_temperature": 14.1,
        "precipitation_probability": 0,
        "rain": 0.0,
        "surface_pressure": 962.9
    },
    {
        "temperature": 17.0,
        "relative_humidity": 53,
        "dew_point": 7.4,
        "apparent_temperature": 13.7,
        "precipitation_probability": 0,
        "rain": 0.0,
        "surface_pressure": 963.7
    },
    {
        "temperature": 17.1,
        "relative_humidity": 53,
        "dew_point": 7.4,
        "apparent_temperature": 13.8,
        "precipitation_probability": 0,
        "rain": 0.0,
        "surface_pressure": 964.9
    },
    {
        "temperature": 17.4,
        "relative_humidity": 51,
        "dew_point": 7.2,
        "apparent_temperature": 14.1,
        "precipitation_probability": 0,
        "rain": 0.0,
        "surface_pressure": 963.2
    },
    {
        "temperature": 17.6,
        "relative_humidity": 51,
        "dew_point": 7.3,
        "apparent_temperature": 14.2,
        "precipitation_probability": 0,
        "rain": 0.0,
        "surface_pressure": 962.2
    },
    {
        "temperature": 17.4,
        "relative_humidity": 51,
        "dew_point": 7.2,
        "apparent_temperature": 14.1,
        "precipitation_probability": 0,
        "rain": 0.0,
        "surface_pressure": 963.2
    },
    {
        "temperature": 17.4,
        "relative_humidity": 51,
        "dew_point": 7.1,
        "apparent_temperature": 14.1,
        "precipitation_probability": 0,
        "rain": 0.0,
        "surface_pressure": 962.5
    },
    {
        "temperature": 17.4,
        "relative_humidity": 51,
        "dew_point": 7.1,
        "apparent_temperature": 14.1,
        "precipitation_probability": 0,
        "rain": 0.0,
        "surface_pressure": 962.4
    },
    {
        "temperature": 17.4,
        "relative_humidity": 51,
        "dew_point": 7.2,
        "apparent_temperature": 14.1,
        "precipitation_probability": 0,
        "rain": 0.0,
        "surface_pressure": 963.2
    },
    {
        "temperature": 16.9,
        "relative_humidity": 53,
        "dew_point": 7.2,
        "apparent_temperature": 12.8,
        "precipitation_probability": 0,
        "rain": 0.0,
        "surface_pressure": 962.3
    },
    {
        "temperature": 17.4,
        "relative_humidity": 51,
        "dew_point": 7.1,
        "apparent_temperature": 14.1,
        "precipitation_probability": 0,
        "rain": 0.0,
        "surface_pressure": 962.4
    },
    {
        "temperature": 17.0,
        "relative_humidity": 53,
        "dew_point": 7.3,
        "apparent_temperature": 13.6,
        "precipitation_probability": 0,
        "rain": 0.0,
        "surface_pressure": 962.9
    },
    {
        "temperature": 16.9,
        "relative_humidity": 53,
        "dew_point": 7.2,
        "apparent_temperature": 12.8,
        "precipitation_probability": 0,
        "rain": 0.0,
        "surface_pressure": 962.4
    },
    {
        "temperature": 17.6,
        "relative_humidity": 51,
        "dew_point": 7.3,
        "apparent_temperature": 14.2,
        "precipitation_probability": 3,
        "rain": 0.0,
        "surface_pressure": 961.9
    },
    {
        "temperature": 17.5,
        "relative_humidity": 51,
        "dew_point": 7.2,
        "apparent_temperature": 14.2,
        "precipitation_probability": 0,
        "rain": 0.0,
        "surface_pressure": 964.3
    },
    {
        "temperature": 16.9,
        "relative_humidity": 53,
        "dew_point": 7.3,
        "apparent_temperature": 13.6,
        "precipitation_probability": 0,
        "rain": 0.0,
        "surface_pressure": 962.6
    },
    {
        "temperature": 17.0,
        "relative_humidity": 53,
        "dew_point": 7.3,
        "apparent_temperature": 13.6,
        "precipitation_probability": 0,
        "rain": 0.0,
        "surface_pressure": 963.0
    },
    {
        "temperature": 17.4,
        "relative_humidity": 51,
        "dew_point": 7.1,
        "apparent_temperature": 14.1,
        "precipitation_probability": 0,
        "rain": 0.0,
        "surface_pressure": 962.6
    },
    {
        "temperature": 17.3,
        "relative_humidity": 51,
        "dew_point": 7.1,
        "apparent_temperature": 14.1,
        "precipitation_probability": 0,
        "rain": 0.0,
        "surface_pressure": 962.3
    },
    {
        "temperature": 17.0,
        "relative_humidity": 53,
        "dew_point": 7.3,
        "apparent_temperature": 13.7,
        "precipitation_probability": 0,
        "rain": 0.0,
        "surface_pressure": 963.6
    },
    {
        "temperature": 17.5,
        "relative_humidity": 51,
        "dew_point": 7.2,
        "apparent_temperature": 14.2,
        "precipitation_probability": 0,
        "rain": 0.0,
        "surface_pressure": 964.6
    },
    {
        "temperature": 16.9,
        "relative_humidity": 53,
        "dew_point": 7.2,
        "apparent_temperature": 12.8,
        "precipitation_probability": 0,
        "rain": 0.0,
        "surface_pressure": 962.4
    },
    {
        "temperature": 16.9,
        "relative_humidity": 53,
        "dew_point": 7.3,
        "apparent_temperature": 13.0,
        "precipitation_probability": 0,
        "rain": 0.0,
        "surface_pressure": 961.9
    },
    {
        "temperature": 16.9,
        "relative_humidity": 53,
        "dew_point": 7.2,
        "apparent_temperature": 12.8,
        "precipitation_probability": 0,
        "rain": 0.0,
        "surface_pressure": 962.7
    },
    {
        "temperature": 17.1,
        "relative_humidity": 53,
        "dew_point": 7.5,
        "apparent_temperature": 13.8,
        "precipitation_probability": 0,
        "rain": 0.0,
        "surface_pressure": 965.8
    },
    {
        "temperature": 17.6,
        "relative_humidity": 51,
        "dew_point": 7.3,
        "apparent_temperature": 14.2,
        "precipitation_probability": 3,
        "rain": 0.0,
        "surface_pressure": 962.3
    },
    {
        "temperature": 17.0,
        "relative_humidity": 53,
        "dew_point": 7.3,
        "apparent_temperature": 13.6,
        "precipitation_probability": 0,
        "rain": 0.0,
        "surface_pressure": 963.0
    }
]