[
    {
        "temperature": 20.3,
        "relative_humidity": 50,
        "dew_point": 9.6,
        "apparent_temperature": 19.8,
        "precipitation_probability": 0,
        "rain": 0.0,
        "surface_pressure": 987.4
    },
    {
        "temperature": 20.6,
        "relative_humidity": 49,
        "dew_point": 9.5,
        "apparent_temperature": 19.9,
        "precipitation_probability": 0,
        "rain": 0.0,
        "surface_pressure": 989.0
    },
    {
        "temperature": 20.6,
        "relative_humidity": 49,
        "dew_point": 9.5,
        "apparent_temperature": 19.9,
        "precipitation_probability": 0,
        "rain": 0.0,
        "surface_pressure": 988.4
    },
    {
        "temperature": 20.5,
        "relative_humidity": 56,
        "dew_point": 11.4,
        "apparent_temperature": 20.6,
        "precipitation_probability": 0,
        "rain": 0.0,
        "surface_pressure": 989.1
    },
    {
        "temperature": 20.5,
        "relative_humidity": 56,
        "dew_point": 11.4,
        "apparent_temperature": 20.7,
        "precipitation_probability": 0,
        "rain": 0.0,
        "surface_pressure": 990.4
    },
    {
        "temperature": 20.6,
        "relative_humidity": 49,
        "dew_point": 9.5,
        "apparent_temperature": 19.9,
        "precipitation_probability": 0,
        "rain": 0.0,
        "surface_pressure": 988.7
    },
    {
        "temperature": 21.0,
        "relative_humidity": 49,
        "dew_point": 9.8,
        "apparent_temperature": 20.3,
        "precipitation_probability": 0,
        "rain": 0.0,
        "surface_pressure": 988.0
    },
    {
        "temperature": 20.6,
        "relative_humidity": 49,
        "dew_point": 9.5,
        "apparent_temperature": 19.9,
        "precipitation_probability": 0,
        "rain": 0.0,
        "surface_pressure": 988.7
    },
    {
        "temperature": 20.6,
        "relative_humidity": 49,
        "dew_point": 9.5,
        "apparent_temperature": 19.9,
        "precipitation_probability": 0,
        "rain": 0.0,
        "surface_pressure": 988.0
    },
    {
        "temperature": 20.6,
        "relative_humidity": 49,
        "dew_point": 9.5,
        "apparent_temperature": 19.9,
        "precipitation_probability": 0,
        "rain": 0.0,
        "surface_pressure": 987.9
    },
    {
        "temperature": 20.6,
        "relative_humidity": 49,
        "dew_point": 9.5,
        "apparent_temperature": 19.9,
        "precipitation_probability": 0,
        "rain": 0.0,
        "surface_pressure": 988.7
    },
    {
        "temperature": 20.4,
        "relative_humidity": 50,
        "dew_point": 9.6,
        "apparent_temperature": 19.8,
        "precipitation_probability": 0,
        "rain": 0.0,
        "surface_pressure": 987.9
    },
    {
        "temperature": 20.6,
        "relative_humidity": 49,
        "dew_point": 9.5,
        "apparent_temperature": 19.9,
        "precipitation_probability": 0,
        "rain": 0.0,
        "surface_pressure": 987.9
    },
    {
        "temperature": 20.4,
        "relative_humidity": 56,
        "dew_point": 11.3,
        "apparent_temperature": 20.6,
        "precipitation_probability": 0,
        "rain": 0.0,
        "surface_pressure": 988.3
    },
    {
        "temperature": 20.4,
        "relative_humidity": 50,
        "dew_point": 9.6,
        "apparent_temperature": 19.8,
        "precipitation_probability": 0,
        "rain": 0.0,
        "surface_pressure": 988.0
    },
    {
        "temperature": 20.9,
        "relative_humidity": 49,
        "dew_point": 9.8,
        "apparent_temperature": 20.2,
        "precipitation_probability": 0,
        "rain": 0.0,
        "surface_pressure": 987.6
    },
    {
        "temperature": 20.7,
        "relative_humidity": 49,
        "dew_point": 9.6,
        "apparent_temperature": 20.0,
        "precipitation_probability": 0,
        "rain": 0.0,
        "surface_pressure": 989.9
    },
    {
        "temperature": 20.4,
        "relative_humidity": 56,
        "dew_point": 11.3,
        "apparent_temperature": 20.5,
        "precipitation_probability": 0,
        "rain": 0.0,
        "surface_pressure": 988.0
    },
    {
        "temperature": 20.4,
        "relative_humidity": 56,
        "dew_point": 11.3,
        "apparent_temperature": 20.6,
        "precipitation_probability": 0,
        "rain": 0.0,
        "surface_pressure": 988.5
    },
    {
        "temperature": 20.6,
        "relative_humidity": 49,
        "dew_point": 9.5,
        "apparent_temperature": 19.9,
        "precipitation_probability": 0,
        "rain": 0.0,
        "surface_pressure": 988.1
    },
    {
        "temperature": 20.5,
        "relative_humidity": 49,
        "dew_point": 9.5,
        "apparent_temperature": 19.9,
        "precipitation_probability": 0,
        "rain": 0.0,
        "surface_pressure": 987.8
    },
    {
        "temperature": 20.4,
        "relative_humidity": 56,
        "dew_point": 11.4,
        "apparent_temperature": 20.6,
        "precipitation_probability": 0,
        "rain": 0.0,
        "surface_pressure": 989.0
    },
    {
        "temperature": 20.7,
        "relative_humidity": 49,
        "dew_point": 9.6,
        "apparent_temperature": 20.0,
        "precipitation_probability": 0,
        "rain": 0.0,
        "surface_pressure": 990.1
    },
    {
        "temperature": 20.4,
        "relative_humidity": 50,
        "dew_point": 9.6,
        "apparent_temperature": 19.8,
        "precipitation_probability": 0,
        "rain": 0.0,
        "surface_pressure": 988.0
    },
    {
        "temperature": 21.9,
        "relative_humidity": 51,
        "dew_point": 11.3,
        "apparent_temperature": 21.8,
        "precipitation_probability": 0,
        "rain": 0.0,
        "surface_pressure": 987.7
    },
    {
        "temperature": 20.4,
        "relative_humidity": 50,
        "dew_point": 9.6,
        "apparent_temperature": 19.8,
        "precipitation_probability": 0,
        "rain": 0.0,
        "surface_pressure": 988.2
    },
    {
        "temperature": 20.6,
        "relative_humidity": 56,
        "dew_point": 11.5,
        "apparent_temperature": 20.8,
        "precipitation_probability": 0,
        "rain": 0.0,
        "surface_pressure": 991.3
    },
    {
        "temperature": 21.0,
        "relative_humidity": 49,
        "dew_point": 9.8,
        "apparent_temperature": 20.3,
        "precipitation_probability": 0,
        "rain": 0.0,
        "surface_pressure": 988.1
    },
    {
        "temperature": 20.4,
        "relative_humidity": 56,
        "dew_point": 11.3,
        "apparent_temperature": 20.6,
        "precipitation_probability": 0,
        "rain": 0.0,
        "surface_pressure": 988.5
    }
]